diproperm/DiProPerm.py
diproperm/__init__.py
diproperm/classifiers.py
diproperm/viz.py
diproperm/viz_utils.py
diproperm/tests/__init__.py
diproperm/tests/test_DiProPerm.py
diproperm-0.0.3.dist-info/METADATA
diproperm-0.0.3.dist-info/WHEEL
diproperm-0.0.3.dist-info/top_level.txt
diproperm-0.0.3.dist-info/RECORD
