Metadata-Version: 2.1
Name: diproperm
Version: 0.0.3
Summary: DiProPerm for high dimensional hypothesis testing.
Home-page: https://github.com/idc9/diproperm
Author: Iain Carmichael
Author-email: idc9@cornell.edu
License: MIT
Platform: UNKNOWN
Classifier: License :: OSI Approved :: MIT License
Classifier: Programming Language :: Python
Classifier: Programming Language :: Python :: 3
Classifier: Programming Language :: Python :: 3.6
Classifier: Programming Language :: Python :: Implementation :: PyPy
Classifier: Intended Audience :: Science/Research
Requires-Python: >=3.6.0
Requires-Dist: numpy
Requires-Dist: scipy
Requires-Dist: seaborn
Requires-Dist: matplotlib
Requires-Dist: sklearn
